hypeme/__init__.py
hypeme-0.1.3.dist-info/LICENSE
hypeme-0.1.3.dist-info/WHEEL
hypeme-0.1.3.dist-info/METADATA
hypeme-0.1.3.dist-info/RECORD
